docx_search/__init__.py
docx_search/main.py
docx_search-1.0.1.dist-info/LICENSE
docx_search-1.0.1.dist-info/METADATA
docx_search-1.0.1.dist-info/WHEEL
docx_search-1.0.1.dist-info/top_level.txt
docx_search-1.0.1.dist-info/RECORD
